catdv_resolve/__init__.py
catdv_resolve/__main__.py
catdv_resolve/bootstrap.py
catdv_resolve/config.py
catdv_resolve/exceptions.py
catdv_resolve/fcpxml.py
catdv_resolve/main.py
catdv_resolve/resolve.py
catdv_resolve/system_platform.py
catdv_resolve/webview_api.py
catdv_resolve/static/index.html
catdv_resolve/static/style.css
catdv_resolve/static/resources/logo.png
catdv_resolve-1.3.11.dist-info/LICENSE.txt
catdv_resolve-1.3.11.dist-info/METADATA
catdv_resolve-1.3.11.dist-info/WHEEL
catdv_resolve-1.3.11.dist-info/top_level.txt
catdv_resolve-1.3.11.dist-info/RECORD
