Metadata-Version: 2.1
Name: catdv-resolve
Version: 1.3.11
Summary: DaVinci Resolve script/plugin for interfacing with CatDV Web Panel
Home-page: https://github.com/Lordfirespeed/CatDVResolve
Author: Quantum Corporation
Author-email: developer@catdv.com
Project-URL: Bug Tracker, https://github.com/Lordfirespeed/CatDVResolve/issues
Project-URL: repository, https://github.com/Lordfirespeed/CatDVResolve
Classifier: Programming Language :: Python :: 3
Classifier: License :: OSI Approved :: MIT License
Classifier: Operating System :: OS Independent
Requires-Python: <3.11,>=3.7
License-File: LICENSE.txt
Requires-Dist: future (==0.18.2)
Requires-Dist: pythonnet (==3.0.0a2)
Requires-Dist: clr-loader (==0.1.7)
Requires-Dist: pywebview (<3.8,>=3.7.0)
Requires-Dist: flask (<=3.0.0,>=2.0.3)
Requires-Dist: pygetwindow (==0.0.9)
Requires-Dist: requests (>=2.27.1)
Requires-Dist: pywebview[pyside6] (<3.8,>=3.7.0) ; platform_system != "Windows"
Requires-Dist: PyQt6-WebEngine (<7.0,>=6.4) ; platform_system != "Windows"
Requires-Dist: pyobjc-framework-Quartz (>=8.5.1) ; platform_system == "Darwin"
